.DS_Store
tests/__init__.py
tests/test_core.py
tests/test_smiles_data.py
tests/test_utils.py
tests/test_visualization.py
visChem/.DS_Store
visChem/__init__.py
visChem/core.py
visChem/smiles_data.py
visChem/utils.py
visChem/visualization.py
visChem/__pycache__/__init__.cpython-310.pyc
visChem/__pycache__/core.cpython-310.pyc
visChem/__pycache__/smiles_data.cpython-310.pyc
visChem/__pycache__/utils.cpython-310.pyc
visChem/__pycache__/visualization.cpython-310.pyc
visChem-0.1.3.dist-info/METADATA
visChem-0.1.3.dist-info/WHEEL
visChem-0.1.3.dist-info/top_level.txt
visChem-0.1.3.dist-info/RECORD
