Metadata-Version: 2.1
Name: visChem
Version: 0.1.3
Summary: A tool for chemical space visualization and clustering.
Author: Steve Niu
Author-email: stevexniu@gmail.com
Classifier: Development Status :: 3 - Alpha
Classifier: Intended Audience :: Science/Research
Classifier: Topic :: Scientific/Engineering :: Chemistry
Classifier: License :: OSI Approved :: MIT License
Classifier: Programming Language :: Python :: 3.6
Requires-Dist: adjusttext (>=0.7.3)
Requires-Dist: hdbscan (>=0.8.27)
Requires-Dist: numpy (>=1.21.2)
Requires-Dist: pandas (>=1.2.3)
Requires-Dist: pillow (>=10.0.0)
Requires-Dist: rdkit (>=2023.3.3)
Requires-Dist: scipy (>=1.5.4)
Requires-Dist: umap-learn (>=0.5.3)
